django_video_encoder/__init__.py
django_video_encoder/admin.py
django_video_encoder/api.py
django_video_encoder/apps.py
django_video_encoder/checks.py
django_video_encoder/errors.py
django_video_encoder/models.py
django_video_encoder/signals.py
django_video_encoder/tasks.py
django_video_encoder/urls.py
django_video_encoder/views.py
django_video_encoder/migrations/0001_initial.py
django_video_encoder/migrations/0001_squashed_0004_remove_format_format.py
django_video_encoder/migrations/0002_auto_20201022_1647.py
django_video_encoder/migrations/0003_auto_20201029_1613.py
django_video_encoder/migrations/0004_remove_format_format.py
django_video_encoder/migrations/__init__.py
example/__init__.py
example/manage.py
example/models.py
example/settings.py
example/urls.py
example/tests/__init__.py
example/tests/test_base.py
django_video_encoder-1.1.1.dist-info/LICENSE.txt
django_video_encoder-1.1.1.dist-info/METADATA
django_video_encoder-1.1.1.dist-info/WHEEL
django_video_encoder-1.1.1.dist-info/top_level.txt
django_video_encoder-1.1.1.dist-info/RECORD
